[
    {
        "EventId": 1,
        "UserTableGUID": "7c642e3c-7dc6-464a-818d-2a91cd47873a",
        "CreatedBy": "Ronak Vachhani",
        "EventTitle": "Birthday Party",
        "EventDate": "2018-08-21T00:00:00",
        "EventStartTime": "2018-10-18T18:30:00",
        "EventEndTime": "2018-10-18T19:30:00",
        "EventAddress1": "Gondal Road, Rajkot, Gujarat, India",
        "EventAddress2": "",
        "City": "Ahmedabad",
        "State": "Gujarat",
        "ZipCode": "",
        "LocationLatitude": 22.2424207,
        "LocationLongitude": 70.8000554,
        "EventMessage": "Ronak's Birthday",
        "PrivacySettings": false,
        "CreateDate": "2018-08-23T11:02:10.47",
        "Venue": "AIS India",
        "EventImage": "",
        "EventGUID": "21a594fb-a9f3-4200-a5d7-01b971a74644",
        "ViewDate": null,
        "id": 0
    },
    {
        "EventId": 2,
        "UserTableGUID": "2a725997-29a6-4d4a-8e48-6c1dd871e30f",
        "CreatedBy": "",
        "EventTitle": "1 year Anniversary",
        "EventDate": "2018-08-14T00:00:00",
        "EventStartTime": "2018-08-31T15:19:00",
        "EventEndTime": "2018-08-31T16:19:00",
        "EventAddress1": "AI Software LLC, Corporate Road, Makarba, Ahmedabad, Gujarat, India",
        "EventAddress2": "",
        "City": "Ahmedabad",
        "State": "Gujarat",
        "ZipCode": "",
        "LocationLatitude": 22.9991213,
        "LocationLongitude": 72.5016971,
        "EventMessage": "",
        "PrivacySettings": false,
        "CreateDate": "2018-08-31T06:50:47",
        "Venue": "Ai software llc",
        "EventImage": "",
        "EventGUID": "321ff7df-6c9c-43ee-8c35-e6dc7627d693",
        "ViewDate": null,
        "id": 1
    },
    {
        "EventId": 3,
        "UserTableGUID": "77209649-5fbf-45d6-8b24-a1dcb08b59d1",
        "CreatedBy": "Vimal Kotadiya",
        "EventTitle": "Techuz",
        "EventDate": "2018-08-31T00:00:00",
        "EventStartTime": "2018-09-05T15:10:00",
        "EventEndTime": "2018-09-05T16:10:00",
        "EventAddress1": "Iscon Mega Mall, Bodakdev, Ahmedabad, Gujarat, India",
        "EventAddress2": "",
        "City": "Ahmedabad",
        "State": "Gujarat",
        "ZipCode": "",
        "LocationLatitude": 23.030513763427734,
        "LocationLongitude": 72.50753784179688,
        "EventMessage": "Technical Event",
        "PrivacySettings": true,
        "CreateDate": "2018-08-31T09:41:26.517",
        "Venue": "Iscon",
        "EventImage": "",
        "EventGUID": "0e76f8bf-f219-4f55-88b5-5323af3335c5",
        "ViewDate": null,
        "id": 2
    },
    {
        "EventId": 4,
        "UserTableGUID": "7c642e3c-7dc6-464a-818d-2a91cd47873a",
        "CreatedBy": "Ronak Vachhani",
        "EventTitle": "Test Event",
        "EventDate": "2018-08-31T00:00:00",
        "EventStartTime": "2018-08-31T16:52:00",
        "EventEndTime": "2018-08-31T17:52:00",
        "EventAddress1": "Ahmedabad, Gujarat, India",
        "EventAddress2": "",
        "City": "Ahmedabad",
        "State": "Gujarat",
        "ZipCode": "",
        "LocationLatitude": 23.022505,
        "LocationLongitude": 72.5713621,
        "EventMessage": "AIS Notes",
        "PrivacySettings": false,
        "CreateDate": "2018-08-31T11:24:14.957",
        "Venue": "AIS Test",
        "EventImage": "",
        "EventGUID": "41e9c47a-f2c4-432a-a341-7625cbe49771",
        "ViewDate": null,
        "id": 3
    },
    {
        "EventId": 5,
        "UserTableGUID": "7c642e3c-7dc6-464a-818d-2a91cd47873a",
        "CreatedBy": "Ronak Vachhani",
        "EventTitle": "Another Test",
        "EventDate": "2018-09-02T00:00:00",
        "EventStartTime": "2018-08-31T16:55:00",
        "EventEndTime": "2018-08-31T17:55:00",
        "EventAddress1": "Rajkot, Gujarat, India",
        "EventAddress2": "",
        "City": "Rajkot",
        "State": "Gujarat",
        "ZipCode": "",
        "LocationLatitude": 22.3038945,
        "LocationLongitude": 70.8021599,
        "EventMessage": "Test",
        "PrivacySettings": false,
        "CreateDate": "2018-08-31T11:25:31.987",
        "Venue": "Test",
        "EventImage": "",
        "EventGUID": "5596c10c-681e-4b7f-a8ba-3b00b02063fa",
        "ViewDate": null,
        "id": 4
    },
    {
        "EventId": 6,
        "UserTableGUID": "77209649-5fbf-45d6-8b24-a1dcb08b59d1",
        "CreatedBy": "Vimal Kotadiya",
        "EventTitle": "Diwali",
        "EventDate": "2018-08-31T00:00:00",
        "EventStartTime": "2018-09-05T17:07:00",
        "EventEndTime": "2018-09-05T18:07:00",
        "EventAddress1": "Noida, Uttar Pradesh, India",
        "EventAddress2": "",
        "City": "Noida",
        "State": "Uttar Pradesh",
        "ZipCode": "",
        "LocationLatitude": 28.5355167388916,
        "LocationLongitude": 77.39102935791016,
        "EventMessage": "test note",
        "PrivacySettings": false,
        "CreateDate": "2018-08-31T11:37:07.647",
        "Venue": "team",
        "EventImage": "",
        "EventGUID": "4788154e-2178-48cc-a1ee-ed5dc9fd6d6f",
        "ViewDate": null,
        "id": 5
    },
    {
        "EventId": 7,
        "UserTableGUID": "92824c3e-8c95-4c79-bb1d-3137bb813e61",
        "CreatedBy": "Piyush Bhatt",
        "EventTitle": "Labor day camp",
        "EventDate": "2018-08-31T00:00:00",
        "EventStartTime": "2018-10-19T17:13:00",
        "EventEndTime": "2018-10-19T18:13:00",
        "EventAddress1": "6067 St Paul Rd, Troy, MI, USA",
        "EventAddress2": "",
        "City": "Troy",
        "State": "MI",
        "ZipCode": "",
        "LocationLatitude": 42.607139587402344,
        "LocationLongitude": -83.15914154052734,
        "EventMessage": "Lets get together and then ride",
        "PrivacySettings": false,
        "CreateDate": "2018-08-31T15:13:47.28",
        "Venue": "House",
        "EventImage": "",
        "EventGUID": "c1b895f5-4ebd-4aec-bfbb-74adaa14383f",
        "ViewDate": null,
        "id": 6
    },
    {
        "EventId": 8,
        "UserTableGUID": "7c642e3c-7dc6-464a-818d-2a91cd47873a",
        "CreatedBy": "Ronak Vachhani",
        "EventTitle": "Picnic",
        "EventDate": "2018-09-03T00:00:00",
        "EventStartTime": "2018-09-05T18:17:00",
        "EventEndTime": "2018-09-05T19:17:00",
        "EventAddress1": "6067, St. Paul Rd",
        "EventAddress2": "",
        "City": "Troy",
        "State": "MI",
        "ZipCode": "",
        "LocationLatitude": 0,
        "LocationLongitude": 0,
        "EventMessage": "",
        "PrivacySettings": false,
        "CreateDate": "2018-09-03T12:49:08.063",
        "Venue": "House",
        "EventImage": "",
        "EventGUID": "94c069db-8757-43a4-9593-265f1ce5e07c",
        "ViewDate": null,
        "id": 7
    },
    {
        "EventId": 9,
        "UserTableGUID": "7c642e3c-7dc6-464a-818d-2a91cd47873a",
        "CreatedBy": "Ronak Vachhani",
        "EventTitle": "Diwali",
        "EventDate": "2018-10-31T00:00:00",
        "EventStartTime": "2018-12-24T18:30:00",
        "EventEndTime": "2018-12-24T19:30:00",
        "EventAddress1": "Palladium, Corporate Road, Makarba, Ahmedabad, Gujarat, India",
        "EventAddress2": "",
        "City": "Ahmedabad",
        "State": "Gujarat",
        "ZipCode": "",
        "LocationLatitude": 22.9991781,
        "LocationLongitude": 72.5014937,
        "EventMessage": "Be there on time!",
        "PrivacySettings": true,
        "CreateDate": "2018-09-05T06:47:56.553",
        "Venue": "AIS Office India",
        "EventImage": "",
        "EventGUID": "ece0079f-7574-4dc2-99e9-75d90838e856",
        "ViewDate": null,
        "id": 8
    },
    {
        "EventId": 10,
        "UserTableGUID": "7c642e3c-7dc6-464a-818d-2a91cd47873a",
        "CreatedBy": "Ronak Vachhani",
        "EventTitle": "Latest Test",
        "EventDate": "2018-09-18T00:00:00",
        "EventStartTime": "2018-09-20T18:30:00",
        "EventEndTime": "2018-09-20T20:05:00",
        "EventAddress1": "Sabarmati Ashram, Ashram Road, Hridaya Kunj, Old Wadaj, Ahmedabad, Gujarat, India",
        "EventAddress2": "",
        "City": "Ahmedabad",
        "State": "Gujarat",
        "ZipCode": "",
        "LocationLatitude": 23.060771942138672,
        "LocationLongitude": 72.58088684082031,
        "EventMessage": "Testing testing...",
        "PrivacySettings": true,
        "CreateDate": "2018-09-05T06:48:31.913",
        "Venue": "Test",
        "EventImage": "",
        "EventGUID": "65a1b13c-ef92-423c-8851-17be2e6d18f0",
        "ViewDate": null,
        "id": 9
    },
    {
        "EventId": 11,
        "UserTableGUID": "7c642e3c-7dc6-464a-818d-2a91cd47873a",
        "CreatedBy": "Ronak Vachhani",
        "EventTitle": "Testing mVite App",
        "EventDate": "2018-09-07T00:00:00",
        "EventStartTime": "2018-09-18T18:51:00",
        "EventEndTime": "2018-09-18T19:51:00",
        "EventAddress1": "Palladium, Corporate Road, Makarba, Ahmedabad, Gujarat, India",
        "EventAddress2": "",
        "City": "Ahmedabad",
        "State": "Gujarat",
        "ZipCode": "",
        "LocationLatitude": 22.999177932739258,
        "LocationLongitude": 72.50149536132812,
        "EventMessage": "mVite Testing",
        "PrivacySettings": false,
        "CreateDate": "2018-09-07T13:22:16.9",
        "Venue": "AIS India",
        "EventImage": "",
        "EventGUID": "92bcdf03-791f-4602-ba75-6996b41413aa",
        "ViewDate": null,
        "id": 10
    },
    {
        "EventId": 12,
        "UserTableGUID": "f16602b1-5b74-4bc0-9462-fea220c9015a",
        "CreatedBy": "shipra verma",
        "EventTitle": "Birthday Party",
        "EventDate": "2018-10-21T00:00:00",
        "EventStartTime": "2018-10-18T13:00:00",
        "EventEndTime": "2018-10-18T14:00:00",
        "EventAddress1": "31100 Woodward Avenue, Royal Oak, MI, USA",
        "EventAddress2": "",
        "City": "Flushing",
        "State": "NY",
        "ZipCode": "",
        "LocationLatitude": 42.51953887939453,
        "LocationLongitude": -83.18534088134766,
        "EventMessage": "",
        "PrivacySettings": false,
        "CreateDate": "2018-10-18T13:10:33.913",
        "Venue": "home",
        "EventImage": "",
        "EventGUID": "65eeeb16-b505-4851-b476-ff4fd8b19a95",
        "ViewDate": null,
        "id": 11
    },
    {
        "EventId": 13,
        "UserTableGUID": "f16602b1-5b74-4bc0-9462-fea220c9015a",
        "CreatedBy": "shipra verma",
        "EventTitle": "Engagement Party",
        "EventDate": "2018-12-23T00:00:00",
        "EventStartTime": "2018-10-19T00:00:00",
        "EventEndTime": "2018-10-19T00:00:00",
        "EventAddress1": "Colaba, Mumbai, Maharashtra, India",
        "EventAddress2": "",
        "City": "Mumbai",
        "State": "Maharashtra",
        "ZipCode": "",
        "LocationLatitude": 18.90670394897461,
        "LocationLongitude": 72.81471252441406,
        "EventMessage": "testing abc ",
        "PrivacySettings": false,
        "CreateDate": "2018-10-18T15:18:03.33",
        "Venue": "taj mahal hotel ",
        "EventImage": "",
        "EventGUID": "e09bfcdb-68a8-4e77-ba34-5873ab92a0d5",
        "ViewDate": null,
        "id": 12
    },
    {
        "EventId": 14,
        "UserTableGUID": "f16602b1-5b74-4bc0-9462-fea220c9015a",
        "CreatedBy": "shipra verma",
        "EventTitle": "test",
        "EventDate": "2018-10-19T00:00:00",
        "EventStartTime": "2018-10-19T16:05:00",
        "EventEndTime": "2018-10-19T17:05:00",
        "EventAddress1": "Abc Drive, Myrtle Beach, SC, USA",
        "EventAddress2": "",
        "City": "Myrtle Beach",
        "State": "South Carolina",
        "ZipCode": "",
        "LocationLatitude": 33.6963439,
        "LocationLongitude": -78.9026616,
        "EventMessage": "",
        "PrivacySettings": false,
        "CreateDate": "2018-10-19T20:05:43.173",
        "Venue": "abc farms",
        "EventImage": "",
        "EventGUID": "aefbddf5-2761-462b-8000-d8c22ca2aa60",
        "ViewDate": null,
        "id": 13
    },
    {
        "EventId": 15,
        "UserTableGUID": "05fde354-a911-4ce6-9737-9ab696ebb377",
        "CreatedBy": "Shipra verma",
        "EventTitle": "Birthday",
        "EventDate": "2018-10-23T00:00:00",
        "EventStartTime": "2018-10-23T11:17:00",
        "EventEndTime": "2018-10-23T12:17:00",
        "EventAddress1": "Rochester Hills, MI, USA",
        "EventAddress2": "",
        "City": "Rochester Hills",
        "State": "Michigan",
        "ZipCode": "",
        "LocationLatitude": 42.65836715698242,
        "LocationLongitude": -83.14993286132812,
        "EventMessage": "Neil turns 3",
        "PrivacySettings": false,
        "CreateDate": "2018-10-22T15:18:55.13",
        "Venue": "3130 fallen oaks ct",
        "EventImage": "",
        "EventGUID": "6262a814-b081-49c1-9cda-21e130d71aeb",
        "ViewDate": null,
        "id": 14
    },
    {
        "EventId": 16,
        "UserTableGUID": "5fd37e9f-1317-47a9-bc5d-9675bb226cf5",
        "CreatedBy": "Ashish Patel",
        "EventTitle": "graduation",
        "EventDate": "2018-10-23T00:00:00",
        "EventStartTime": "2018-10-23T14:12:00",
        "EventEndTime": "2018-10-23T15:12:00",
        "EventAddress1": "3120 Fallen Oak Court, Shelby charter Township, MI, USA",
        "EventAddress2": "",
        "City": "Shelby charter Township",
        "State": "Michigan",
        "ZipCode": "",
        "LocationLatitude": 42.6525993347168,
        "LocationLongitude": -82.98042297363281,
        "EventMessage": "",
        "PrivacySettings": false,
        "CreateDate": "2018-10-22T18:12:56.387",
        "Venue": "abc farms",
        "EventImage": "",
        "EventGUID": "953ff723-06df-4359-adfe-f06f0c922246",
        "ViewDate": null,
        "id": 15
    },
    {
        "EventId": 17,
        "UserTableGUID": "05fde354-a911-4ce6-9737-9ab696ebb377",
        "CreatedBy": "Shipra verma",
        "EventTitle": "House warming ",
        "EventDate": "2018-10-23T00:00:00",
        "EventStartTime": "2018-10-22T14:57:00",
        "EventEndTime": "2018-10-22T15:57:00",
        "EventAddress1": "110 kkk aaa",
        "EventAddress2": "",
        "City": "",
        "State": "",
        "ZipCode": "",
        "LocationLatitude": 42.5431447,
        "LocationLongitude": -83.1364466,
        "EventMessage": "",
        "PrivacySettings": false,
        "CreateDate": "2018-10-22T18:58:34.887",
        "Venue": "55 stering village",
        "EventImage": "",
        "EventGUID": "e39d3635-f3bf-496d-99e7-da7c85b06faa",
        "ViewDate": null,
        "id": 16
    },
    {
        "EventId": 18,
        "UserTableGUID": "5fd37e9f-1317-47a9-bc5d-9675bb226cf5",
        "CreatedBy": "Ashish Patel",
        "EventTitle": "Arush's 4th Birthday",
        "EventDate": "2018-11-18T00:00:00",
        "EventStartTime": "2018-10-26T18:30:00",
        "EventEndTime": "2018-10-26T19:30:00",
        "EventAddress1": "La Marsa Troy, Rochester Road, Troy, MI, USA",
        "EventAddress2": "",
        "City": "Troy",
        "State": "Michigan",
        "ZipCode": "",
        "LocationLatitude": 42.5728069,
        "LocationLongitude": -83.1272592,
        "EventMessage": "",
        "PrivacySettings": false,
        "CreateDate": "2018-10-27T03:03:03.447",
        "Venue": "La Marsa",
        "EventImage": "",
        "EventGUID": "3ddebf79-f3e3-471e-9275-b4619b9022ac",
        "ViewDate": null,
        "id": 17
    },
    {
        "EventId": 19,
        "UserTableGUID": "92824c3e-8c95-4c79-bb1d-3137bb813e61",
        "CreatedBy": "Piyush Bhatt",
        "EventTitle": "Diwali Gathering",
        "EventDate": "2018-11-09T00:00:00",
        "EventStartTime": "2018-10-29T18:30:00",
        "EventEndTime": "2018-10-29T22:30:00",
        "EventAddress1": "6067 St Paul Rd, Troy, MI, USA",
        "EventAddress2": "",
        "City": "Troy",
        "State": "MI",
        "ZipCode": "",
        "LocationLatitude": 42.607139587402344,
        "LocationLongitude": -83.15914154052734,
        "EventMessage": "Dear Friends. Lets celebrate Diwali together on Friday evening with dinner and fire crackers. ",
        "PrivacySettings": false,
        "CreateDate": "2018-10-30T01:19:56.057",
        "Venue": "Our Home",
        "EventImage": "",
        "EventGUID": "417e7bcf-7c8c-463a-8380-f2bfd755c3fc",
        "ViewDate": null,
        "id": 18
    },
    {
        "EventId": 20,
        "UserTableGUID": "2a725997-29a6-4d4a-8e48-6c1dd871e30f",
        "CreatedBy": "",
        "EventTitle": "New Year Party",
        "EventDate": "2018-10-09T00:00:00",
        "EventStartTime": "2018-10-30T02:58:00",
        "EventEndTime": "2018-10-30T03:58:00",
        "EventAddress1": "Ahmedabad, Gujarat, India",
        "EventAddress2": "",
        "City": "Bareja",
        "State": "Bareja",
        "ZipCode": "",
        "LocationLatitude": 23.022505,
        "LocationLongitude": 72.5713621,
        "EventMessage": "",
        "PrivacySettings": false,
        "CreateDate": "2018-10-30T05:28:52.7",
        "Venue": "mera ghar",
        "EventImage": "",
        "EventGUID": "9a081cfb-df2c-4c76-aab5-234dcc0c6e5e",
        "ViewDate": null,
        "id": 19
    },
    {
        "EventId": 21,
        "UserTableGUID": "8e6216a4-098c-41a6-83b9-ed02e0830230",
        "CreatedBy": "Karan Gandhi",
        "EventTitle": "Meeting with Piyush",
        "EventDate": "2018-10-30T00:00:00",
        "EventStartTime": "2018-10-30T20:30:00",
        "EventEndTime": "2018-10-30T21:30:00",
        "EventAddress1": "Troy, MI, USA",
        "EventAddress2": "",
        "City": "Troy",
        "State": "Michigan",
        "ZipCode": "",
        "LocationLatitude": 42.6064095,
        "LocationLongitude": -83.1497751,
        "EventMessage": "",
        "PrivacySettings": false,
        "CreateDate": "2018-10-30T06:31:24.663",
        "Venue": "call",
        "EventImage": "",
        "EventGUID": "0078caf1-e1b9-448f-8586-37d0334d2986",
        "ViewDate": null,
        "id": 20
    },
    {
        "EventId": 22,
        "UserTableGUID": "8e6216a4-098c-41a6-83b9-ed02e0830230",
        "CreatedBy": "Karan Gandhi",
        "EventTitle": "Team meeting",
        "EventDate": "2018-10-30T00:00:00",
        "EventStartTime": "2018-10-30T16:30:00",
        "EventEndTime": "2018-10-30T17:30:00",
        "EventAddress1": "Corporate Road, Makarba, Ahmedabad, Gujarat, India",
        "EventAddress2": "",
        "City": "Ahmedabad",
        "State": "Gujarat",
        "ZipCode": "",
        "LocationLatitude": 23.0038735,
        "LocationLongitude": 72.5040131,
        "EventMessage": "Discuss employee related issues",
        "PrivacySettings": false,
        "CreateDate": "2018-10-30T06:45:53.357",
        "Venue": "Palladium",
        "EventImage": "",
        "EventGUID": "d30db5e6-7aaf-4753-a062-554170fb1dda",
        "ViewDate": null,
        "id": 21
    },
    {
        "EventId": 23,
        "UserTableGUID": "9306fc0e-30e3-49ae-a141-0cd9dbc9449d",
        "CreatedBy": "Shreenil Patel",
        "EventTitle": "Shreenil Test",
        "EventDate": "2018-10-31T00:00:00",
        "EventStartTime": "2018-10-30T12:17:00",
        "EventEndTime": "2018-10-30T13:17:00",
        "EventAddress1": "Palladium, Corporate Road, Makarba, Ahmedabad, Gujarat, India",
        "EventAddress2": "",
        "City": "Ahmedabad",
        "State": "Gujarat",
        "ZipCode": "",
        "LocationLatitude": 22.9991781,
        "LocationLongitude": 72.5014937,
        "EventMessage": "Testing meVite with event",
        "PrivacySettings": false,
        "CreateDate": "2018-10-30T06:48:55.043",
        "Venue": "AIS",
        "EventImage": "",
        "EventGUID": "52edfaeb-7295-4d62-ac1e-ece8739ec217",
        "ViewDate": null,
        "id": 22
    },
    {
        "EventId": 24,
        "UserTableGUID": "e42d419f-45df-41d4-bf7b-6ecb55def17a",
        "CreatedBy": "saee masodkar ",
        "EventTitle": "Birthday party",
        "EventDate": "2018-12-26T00:00:00",
        "EventStartTime": "2018-10-30T19:30:00",
        "EventEndTime": "2018-10-30T23:30:00",
        "EventAddress1": "2329 Massachusetts Avenue, Cambridge, MA, USA",
        "EventAddress2": "",
        "City": "Cambridge",
        "State": "Massachusetts",
        "ZipCode": "",
        "LocationLatitude": 42.3959218,
        "LocationLongitude": -71.1283257,
        "EventMessage": "",
        "PrivacySettings": false,
        "CreateDate": "2018-10-30T07:24:58.837",
        "Venue": "Garden City",
        "EventImage": "",
        "EventGUID": "59ba09f4-0896-4fdb-97aa-f830fbfc99da",
        "ViewDate": null,
        "id": 23
    },
    {
        "EventId": 25,
        "UserTableGUID": "2a725997-29a6-4d4a-8e48-6c1dd871e30f",
        "CreatedBy": "",
        "EventTitle": "birthday",
        "EventDate": "2018-10-25T00:00:00",
        "EventStartTime": "2018-10-30T15:14:00",
        "EventEndTime": "2018-10-30T16:14:00",
        "EventAddress1": "Ahmedabad, Gujarat, India",
        "EventAddress2": "",
        "City": "Bareja",
        "State": "Bareja",
        "ZipCode": "",
        "LocationLatitude": 23.022505,
        "LocationLongitude": 72.5713621,
        "EventMessage": "",
        "PrivacySettings": false,
        "CreateDate": "2018-10-30T09:44:42.827",
        "Venue": "place",
        "EventImage": "",
        "EventGUID": "a35ca088-b709-4e33-aa1a-4845e2de8e9b",
        "ViewDate": null,
        "id": 24
    },
    {
        "EventId": 26,
        "UserTableGUID": "2a725997-29a6-4d4a-8e48-6c1dd871e30f",
        "CreatedBy": "",
        "EventTitle": "abc",
        "EventDate": "2018-10-30T00:00:00",
        "EventStartTime": "2018-10-30T15:16:00",
        "EventEndTime": "2018-10-30T16:16:00",
        "EventAddress1": "Ahmedabad, Gujarat, India",
        "EventAddress2": "",
        "City": "Bareja",
        "State": "Bareja",
        "ZipCode": "",
        "LocationLatitude": 23.022505,
        "LocationLongitude": 72.5713621,
        "EventMessage": "",
        "PrivacySettings": false,
        "CreateDate": "2018-10-30T09:47:41.267",
        "Venue": "abc",
        "EventImage": "",
        "EventGUID": "1a484cd2-25e0-4138-83a8-ac263a501658",
        "ViewDate": null,
        "id": 25
    },
    {
        "EventId": 27,
        "UserTableGUID": "a7ef7171-4480-4752-bd3e-4f234958e3cc",
        "CreatedBy": "hemal trivedi",
        "EventTitle": "Diwali Get together",
        "EventDate": "2018-08-11T00:00:00",
        "EventStartTime": "2018-10-31T09:30:00",
        "EventEndTime": "2018-10-31T21:00:00",
        "EventAddress1": "Bopal, Ahmedabad, Gujarat, India",
        "EventAddress2": "",
        "City": "Ahmedabad",
        "State": "Gujarat",
        "ZipCode": "",
        "LocationLatitude": 23.0336769,
        "LocationLongitude": 72.4634117,
        "EventMessage": "RSVP",
        "PrivacySettings": true,
        "CreateDate": "2018-10-31T03:01:39.387",
        "Venue": "home",
        "EventImage": "",
        "EventGUID": "d081ff08-31ae-4df0-b8fc-4a3964adeb0d",
        "ViewDate": null,
        "id": 26
    },
    {
        "EventId": 28,
        "UserTableGUID": "cc60a87b-5565-4c53-bc1d-2f2710fca6a1",
        "CreatedBy": "",
        "EventTitle": "bday",
        "EventDate": "2018-10-30T00:00:00",
        "EventStartTime": "2018-10-31T17:12:00",
        "EventEndTime": "2018-10-31T18:12:00",
        "EventAddress1": "Ð.Ð. - KOTLOVI SLAVONSKI BROD, Slavonski Brod, Croatia",
        "EventAddress2": "",
        "City": "Slavonski Brod",
        "State": "",
        "ZipCode": "",
        "LocationLatitude": 45.1643622,
        "LocationLongitude": 18.0114006,
        "EventMessage": "hsejdj",
        "PrivacySettings": false,
        "CreateDate": "2018-10-31T11:42:58.423",
        "Venue": "hdjd",
        "EventImage": "",
        "EventGUID": "62e5e1ff-3273-4a67-bc58-88a04a2b755d",
        "ViewDate": null,
        "id": 27
    },
    {
        "EventId": 29,
        "UserTableGUID": "ac98d21c-8713-413d-b3d7-e859a04cc34b",
        "CreatedBy": "Prasad Pawar",
        "EventTitle": "Game Night",
        "EventDate": "2018-11-09T00:00:00",
        "EventStartTime": "2018-11-05T18:00:00",
        "EventEndTime": "2018-11-05T19:00:00",
        "EventAddress1": "Flat no. 16, Arvind Apartments, Taware colony Pune-411009 ",
        "EventAddress2": "",
        "City": "Pune",
        "State": "Maharashtra",
        "ZipCode": "",
        "LocationLatitude": 0,
        "LocationLongitude": 0,
        "EventMessage": "",
        "PrivacySettings": false,
        "CreateDate": "2018-11-05T07:29:59.85",
        "Venue": "My Place",
        "EventImage": "",
        "EventGUID": "af1e6af3-67a7-43bc-b3c5-d7a6b63ff423",
        "ViewDate": null,
        "id": 28
    },
    {
        "EventId": 30,
        "UserTableGUID": "f4193605-c5e3-442f-9fae-c8f19a6f5701",
        "CreatedBy": "",
        "EventTitle": "Teagn’s 18th sleepover Birthday Party",
        "EventDate": "2018-11-24T00:00:00",
        "EventStartTime": "2018-11-07T20:00:00",
        "EventEndTime": "2018-11-07T05:00:00",
        "EventAddress1": "Newark, OH, USA",
        "EventAddress2": "",
        "City": "Newark",
        "State": "OH",
        "ZipCode": "",
        "LocationLatitude": 40.0581205,
        "LocationLongitude": -82.4012642,
        "EventMessage": "",
        "PrivacySettings": false,
        "CreateDate": "2018-11-07T06:01:46.297",
        "Venue": "Cabin in Newark, OH",
        "EventImage": "",
        "EventGUID": "62762fe2-fe0c-40c3-94b7-04f031038790",
        "ViewDate": null,
        "id": 29
    },
    {
        "EventId": 31,
        "UserTableGUID": "5b03b151-7e19-45a0-ba63-66f75a684eab",
        "CreatedBy": "Jay Patel",
        "EventTitle": "Bday party",
        "EventDate": "2018-11-07T00:00:00",
        "EventStartTime": "2018-11-07T16:10:00",
        "EventEndTime": "2018-11-07T17:10:00",
        "EventAddress1": "11847 Barrymore Drive, Frisco, TX, USA",
        "EventAddress2": "",
        "City": "Frisco",
        "State": "TX",
        "ZipCode": "",
        "LocationLatitude": 33.1365595,
        "LocationLongitude": -96.7762313,
        "EventMessage": "Please come on time ",
        "PrivacySettings": false,
        "CreateDate": "2018-11-07T23:11:33.917",
        "Venue": "ABC",
        "EventImage": "",
        "EventGUID": "8fb065a0-4c71-4aac-b68b-1c11b623a9de",
        "ViewDate": null,
        "id": 30
    },
    {
        "EventId": 32,
        "UserTableGUID": "2d073705-468c-4a2f-bd64-0244a81cb5da",
        "CreatedBy": "",
        "EventTitle": "Test ",
        "EventDate": "2018-11-13T00:00:00",
        "EventStartTime": "2018-11-13T09:40:00",
        "EventEndTime": "2018-11-13T10:40:00",
        "EventAddress1": "201 Elizabeth Street, Sydney NSW, Australia",
        "EventAddress2": "",
        "City": "Sydney",
        "State": "NSW",
        "ZipCode": "",
        "LocationLatitude": -33.8738569,
        "LocationLongitude": 151.2094246,
        "EventMessage": "",
        "PrivacySettings": false,
        "CreateDate": "2018-11-12T19:41:22.873",
        "Venue": "Office",
        "EventImage": "",
        "EventGUID": "28e5b133-85cd-479b-80b8-c77dba0b7690",
        "ViewDate": null,
        "id": 31
    },
    {
        "EventId": 33,
        "UserTableGUID": "8e6216a4-098c-41a6-83b9-ed02e0830230",
        "CreatedBy": "Karan Gandhi",
        "EventTitle": "meeting with ronk",
        "EventDate": "2018-11-14T00:00:00",
        "EventStartTime": "2018-11-14T00:00:00",
        "EventEndTime": "2018-11-14T18:08:00",
        "EventAddress1": "Palladium, Lower Parel, Senapati Bapat Marg, Lower Parel, Mumbai, Maharashtra, India",
        "EventAddress2": "",
        "City": "Mumbai",
        "State": "Maharashtra",
        "ZipCode": "",
        "LocationLatitude": 18.9941995,
        "LocationLongitude": 72.8241344,
        "EventMessage": "",
        "PrivacySettings": false,
        "CreateDate": "2018-11-14T11:40:09.893",
        "Venue": "abad",
        "EventImage": "",
        "EventGUID": "daecd6e9-dd98-445a-9540-51e6b322fe8b",
        "ViewDate": null,
        "id": 32
    },
    {
        "EventId": 34,
        "UserTableGUID": "92824c3e-8c95-4c79-bb1d-3137bb813e61",
        "CreatedBy": "Piyush Bhatt",
        "EventTitle": "Clinician App Meeting",
        "EventDate": "2018-11-30T00:00:00",
        "EventStartTime": "2018-11-30T09:29:00",
        "EventEndTime": "2018-11-30T10:29:00",
        "EventAddress1": "Residential Home Health and Residential Hospice, Corporate Drive, Troy, MI, USA",
        "EventAddress2": "",
        "City": "Troy",
        "State": "MI",
        "ZipCode": "",
        "LocationLatitude": 42.595550537109375,
        "LocationLongitude": -83.17020416259766,
        "EventMessage": "",
        "PrivacySettings": false,
        "CreateDate": "2018-11-30T15:30:01.453",
        "Venue": "Office",
        "EventImage": "",
        "EventGUID": "1a45c92e-b3fe-4b09-8162-4c326c795064",
        "ViewDate": null,
        "id": 33
    },
    {
        "EventId": 35,
        "UserTableGUID": "38f9ae7a-c4e7-4ac1-97fd-ddeccfd53d8a",
        "CreatedBy": "",
        "EventTitle": "Bhadresh Birthday",
        "EventDate": "2018-12-11T00:00:00",
        "EventStartTime": "2018-12-10T00:00:00",
        "EventEndTime": "2018-12-10T00:00:00",
        "EventAddress1": "AI Software LLC, Stephenson Highway, Troy, MI, USA",
        "EventAddress2": "",
        "City": "Troy",
        "State": "Michigan",
        "ZipCode": "",
        "LocationLatitude": 42.54277420043945,
        "LocationLongitude": -83.11822509765625,
        "EventMessage": "",
        "PrivacySettings": false,
        "CreateDate": "2018-12-10T15:41:32.67",
        "Venue": "office",
        "EventImage": "",
        "EventGUID": "8de2df9f-8b46-4375-9f06-e447bb1d9d67",
        "ViewDate": null,
        "id": 34
    },
    {
        "EventId": 36,
        "UserTableGUID": "79307f31-7554-4193-8f92-4f35b2858777",
        "CreatedBy": "",
        "EventTitle": "Andrea’s 36th Celebration",
        "EventDate": "2019-01-01T00:00:00",
        "EventStartTime": "2018-12-16T18:15:00",
        "EventEndTime": "2018-12-16T20:15:00",
        "EventAddress1": "3008 Maple Avenue, Dallas, TX, USA",
        "EventAddress2": "",
        "City": "Dallas",
        "State": "TX",
        "ZipCode": "",
        "LocationLatitude": 32.79850769042969,
        "LocationLongitude": -96.80742645263672,
        "EventMessage": "RSVP by Dec 26th ",
        "PrivacySettings": true,
        "CreateDate": "2018-12-15T19:08:25.373",
        "Venue": "Nick & Sam’s Steakhouse",
        "EventImage": "",
        "EventGUID": "8f0838bb-4549-4754-ab37-a827db65ba46",
        "ViewDate": null,
        "id": 35
    },
    {
        "EventId": 37,
        "UserTableGUID": "b95a39d7-a8a4-4ba3-9865-570ad04b3e0c",
        "CreatedBy": "Priya Patel",
        "EventTitle": "Amairas Birthday Party",
        "EventDate": "2018-12-26T00:00:00",
        "EventStartTime": "2018-12-25T18:30:00",
        "EventEndTime": "2018-12-25T20:30:00",
        "EventAddress1": "2422 Cedar Knoll Drive, Troy, MI, USA",
        "EventAddress2": "",
        "City": "Troy",
        "State": "Michigan",
        "ZipCode": "",
        "LocationLatitude": 42.56422424316406,
        "LocationLongitude": -83.10008239746094,
        "EventMessage": "",
        "PrivacySettings": false,
        "CreateDate": "2018-12-26T01:55:10.967",
        "Venue": "Pump it up",
        "EventImage": "",
        "EventGUID": "7f114b66-9bbf-427b-b047-35221df75e2b",
        "ViewDate": null,
        "id": 36
    },
    {
        "EventId": 38,
        "UserTableGUID": "b95a39d7-a8a4-4ba3-9865-570ad04b3e0c",
        "CreatedBy": "Priya Patel",
        "EventTitle": "Test",
        "EventDate": "2018-12-27T00:00:00",
        "EventStartTime": "2018-12-25T19:17:00",
        "EventEndTime": "2018-12-25T20:17:00",
        "EventAddress1": "24220 Woodward Avenue, Pleasant Ridge, MI, USA",
        "EventAddress2": "",
        "City": "Pleasant Ridge",
        "State": "Michigan",
        "ZipCode": "",
        "LocationLatitude": 42.473140716552734,
        "LocationLongitude": -83.14269256591797,
        "EventMessage": "",
        "PrivacySettings": false,
        "CreateDate": "2018-12-26T02:00:35.137",
        "Venue": "test",
        "EventImage": "",
        "EventGUID": "4c90f80d-339e-430c-affe-a735af6ee8db",
        "ViewDate": null,
        "id": 37
    },
    {
        "EventId": 39,
        "UserTableGUID": "4cd11a0f-6527-4a95-af7e-eed3592dd7d8",
        "CreatedBy": "",
        "EventTitle": "Who Dat Turning 50",
        "EventDate": "2019-01-18T00:00:00",
        "EventStartTime": "2018-12-27T18:00:00",
        "EventEndTime": "2018-12-27T19:00:00",
        "EventAddress1": "Ruston, LA, USA",
        "EventAddress2": "",
        "City": "Ruston",
        "State": "LA",
        "ZipCode": "",
        "LocationLatitude": 32.5232048034668,
        "LocationLongitude": -92.63792419433594,
        "EventMessage": "",
        "PrivacySettings": true,
        "CreateDate": "2018-12-27T16:27:24.283",
        "Venue": "Landry’s ",
        "EventImage": "",
        "EventGUID": "4f0639af-c551-4d91-a591-4acd5927113e",
        "ViewDate": null,
        "id": 38
    },
    {
        "EventId": 40,
        "UserTableGUID": "59811a58-867b-4077-ab0f-f0bd1de02bed",
        "CreatedBy": "Sam Park",
        "EventTitle": "ROTC New Year's greetings",
        "EventDate": "2019-01-19T00:00:00",
        "EventStartTime": "2019-01-02T18:00:00",
        "EventEndTime": "2019-01-02T20:00:00",
        "EventAddress1": "4886 E Independence Blvd, Charlotte, NC, USA",
        "EventAddress2": "",
        "City": "Charlotte",
        "State": "NC",
        "ZipCode": "",
        "LocationLatitude": 35.1904182434082,
        "LocationLongitude": -80.76332092285156,
        "EventMessage": "www.chinabuffet.org",
        "PrivacySettings": false,
        "CreateDate": "2019-01-03T01:31:17.24",
        "Venue": "China buffet",
        "EventImage": "",
        "EventGUID": "b357a84c-001d-413e-9727-87afdacf9b2f",
        "ViewDate": null,
        "id": 39
    },
    {
        "EventId": 41,
        "UserTableGUID": "59811a58-867b-4077-ab0f-f0bd1de02bed",
        "CreatedBy": "Sam Park",
        "EventTitle": "Missionary History Seminar of Korea",
        "EventDate": "2019-01-26T00:00:00",
        "EventStartTime": "2019-01-02T17:00:00",
        "EventEndTime": "2019-01-02T20:00:00",
        "EventAddress1": "7121 Delta Lake Drive, Charlotte, NC, USA",
        "EventAddress2": "",
        "City": "Charlotte",
        "State": "NC",
        "ZipCode": "",
        "LocationLatitude": 35.252891540527344,
        "LocationLongitude": -80.73361206054688,
        "EventMessage": "\n",
        "PrivacySettings": false,
        "CreateDate": "2019-01-03T01:55:13.957",
        "Venue": "Bethel Korean ARP Church",
        "EventImage": "",
        "EventGUID": "5af5cee3-4c84-4375-a2cd-86e8d53cbc76",
        "ViewDate": null,
        "id": 40
    },
    {
        "EventId": 42,
        "UserTableGUID": "291ce4c5-f507-4c36-9981-5a3882dcf2cc",
        "CreatedBy": "Eva Britton",
        "EventTitle": "Bitches Love Brunch ",
        "EventDate": "2019-03-02T00:00:00",
        "EventStartTime": "2019-01-06T14:30:00",
        "EventEndTime": "2019-01-06T17:30:00",
        "EventAddress1": "11502 Summer Oak Drive, Germantown, MD, USA",
        "EventAddress2": "",
        "City": "Germantown",
        "State": "MD",
        "ZipCode": "",
        "LocationLatitude": 39.162871,
        "LocationLongitude": -77.241314,
        "EventMessage": "",
        "PrivacySettings": true,
        "CreateDate": "2019-01-06T17:18:45.763",
        "Venue": "My house ",
        "EventImage": "",
        "EventGUID": "6251c946-f783-4e32-a828-bb85a92bc203",
        "ViewDate": null,
        "id": 41
    },
    {
        "EventId": 43,
        "UserTableGUID": "63aaed28-1a39-4645-8925-9bf46006979a",
        "CreatedBy": "",
        "EventTitle": "Queen Ramona’s Birthday Celebration",
        "EventDate": "2019-01-19T00:00:00",
        "EventStartTime": "2019-01-16T20:30:00",
        "EventEndTime": "2019-01-16T01:00:00",
        "EventAddress1": "Firebirds Wood Fired Grill, 3200 Village Market Place, Morrisville, NC, USA",
        "EventAddress2": "",
        "City": "Raleigh",
        "State": "NC",
        "ZipCode": "",
        "LocationLatitude": 35.8077323,
        "LocationLongitude": -78.8187148,
        "EventMessage": "We can meet up for bowling around 6pm before heading to dinner at 8:30pm.",
        "PrivacySettings": true,
        "CreateDate": "2019-01-09T20:00:43.92",
        "Venue": "Firebirds Wood Fired Grill",
        "EventImage": "",
        "EventGUID": "d6ae9823-5526-4ecb-8837-ad59564ee8f1",
        "ViewDate": null,
        "id": 42
    },
    {
        "EventId": 44,
        "UserTableGUID": "d7fd5f89-0a82-4654-8acd-616cbe53257f",
        "CreatedBy": "Shreenil Patel",
        "EventTitle": "Kite Festival 123",
        "EventDate": "2019-01-15T00:00:00",
        "EventStartTime": "2019-01-11T15:30:00",
        "EventEndTime": "2019-01-11T16:30:00",
        "EventAddress1": "Makarba, Ahmedabad, Gujarat, India",
        "EventAddress2": "",
        "City": "Ahmedabad",
        "State": "Gujarat",
        "ZipCode": "",
        "LocationLatitude": 22.99604034423828,
        "LocationLongitude": 72.49967193603516,
        "EventMessage": "Kites will be provided",
        "PrivacySettings": false,
        "CreateDate": "2019-01-11T06:57:17.937",
        "Venue": "Sabarmati",
        "EventImage": "",
        "EventGUID": "1936952b-65ac-4cc4-aa5d-bee9cbbf5f29",
        "ViewDate": null,
        "id": 43
    },
    {
        "EventId": 45,
        "UserTableGUID": "d7fd5f89-0a82-4654-8acd-616cbe53257f",
        "CreatedBy": "Shreenil Patel",
        "EventTitle": "Test Event 11th Jan",
        "EventDate": "2019-01-11T00:00:00",
        "EventStartTime": "2019-01-11T16:43:00",
        "EventEndTime": "2019-01-11T17:43:00",
        "EventAddress1": "Makarba, Ahmedabad, Gujarat, India",
        "EventAddress2": "",
        "City": "Ahmedabad",
        "State": "Gujarat",
        "ZipCode": "",
        "LocationLatitude": 22.9960402,
        "LocationLongitude": 72.4996699,
        "EventMessage": "test event ",
        "PrivacySettings": false,
        "CreateDate": "2019-01-11T11:39:17.013",
        "Venue": "Ais",
        "EventImage": "",
        "EventGUID": "655d4f16-4680-411f-91fb-731a4cebbc8d",
        "ViewDate": null,
        "id": 44
    },
    {
        "EventId": 46,
        "UserTableGUID": "d7fd5f89-0a82-4654-8acd-616cbe53257f",
        "CreatedBy": "Shreenil Patel",
        "EventTitle": "Test Shreenil",
        "EventDate": "2019-01-11T00:00:00",
        "EventStartTime": "2019-01-11T18:36:00",
        "EventEndTime": "2019-01-11T19:36:00",
        "EventAddress1": "B455 Princes Highway, Jaspers Brush NSW, Australia",
        "EventAddress2": "",
        "City": "Jaspers Brush",
        "State": "New South Wales",
        "ZipCode": "",
        "LocationLatitude": -34.8048874,
        "LocationLongitude": 150.6538329,
        "EventMessage": "notes ",
        "PrivacySettings": false,
        "CreateDate": "2019-01-11T13:07:07.457",
        "Venue": "ais",
        "EventImage": "",
        "EventGUID": "70bb1e02-36f6-4f17-bab8-6d08d1081b79",
        "ViewDate": null,
        "id": 45
    },
    {
        "EventId": 47,
        "UserTableGUID": "d9fd45d0-0815-4602-881f-886a7f494ec1",
        "CreatedBy": "",
        "EventTitle": "Valentine’s Day/Game Night Party",
        "EventDate": "2019-02-16T00:00:00",
        "EventStartTime": "2019-01-14T18:30:00",
        "EventEndTime": "2019-01-14T00:00:00",
        "EventAddress1": "3136 Ampere Avenue, Bronx, NY, USA",
        "EventAddress2": "",
        "City": "New York",
        "State": "NY",
        "ZipCode": "",
        "LocationLatitude": 40.84614181518555,
        "LocationLongitude": -73.82427215576172,
        "EventMessage": "Please join us for a game of Couples Taboo, good eats and lots of laugh...all to celebrate love. ",
        "PrivacySettings": false,
        "CreateDate": "2019-01-14T16:28:43.82",
        "Venue": "Tamika and Charles’s House",
        "EventImage": "",
        "EventGUID": "93d278ab-d4cf-4f44-9771-6533afdb9d27",
        "ViewDate": null,
        "id": 46
    },
    {
        "EventId": 48,
        "UserTableGUID": "d9fd45d0-0815-4602-881f-886a7f494ec1",
        "CreatedBy": "",
        "EventTitle": "Valentine’s Day Game Night",
        "EventDate": "2019-02-16T00:00:00",
        "EventStartTime": "2019-01-14T18:30:00",
        "EventEndTime": "2019-01-14T00:00:00",
        "EventAddress1": "3136 Ampere Ave, Bronx, NY, USA",
        "EventAddress2": "",
        "City": "New York",
        "State": "NY",
        "ZipCode": "",
        "LocationLatitude": 40.846141,
        "LocationLongitude": -73.824273,
        "EventMessage": "Please join us to celebrate love, play a friendly game of Couples Taboo, enjoy some good eats with lots of laughter! ",
        "PrivacySettings": false,
        "CreateDate": "2019-01-14T16:41:32.633",
        "Venue": "Tamika and Charles’s House",
        "EventImage": "",
        "EventGUID": "995d2846-648a-40d0-bdb3-d370b21cd20f",
        "ViewDate": null,
        "id": 47
    },
    {
        "EventId": 49,
        "UserTableGUID": "00eeeecd-c720-4f42-b355-2462e632f0b0",
        "CreatedBy": "",
        "EventTitle": "Anaiyah’s 9th Birthday ",
        "EventDate": "2019-01-27T00:00:00",
        "EventStartTime": "2019-01-24T10:30:00",
        "EventEndTime": "2019-01-24T19:00:00",
        "EventAddress1": "465 F Street, Chula Vista, CA, USA",
        "EventAddress2": "",
        "City": "Chula Vista",
        "State": "CA",
        "ZipCode": "",
        "LocationLatitude": 32.639625549316406,
        "LocationLongitude": -117.08671569824219,
        "EventMessage": "We will be going to SeaWorld a day of fun, then having a birthday dinner after!     Dinner location TBD",
        "PrivacySettings": false,
        "CreateDate": "2019-01-24T16:33:59.073",
        "Venue": "Seaworld San Diego/ Dinner!",
        "EventImage": "",
        "EventGUID": "8f405170-5047-4495-bd40-a47777057de4",
        "ViewDate": null,
        "id": 48
    },
    {
        "EventId": 50,
        "UserTableGUID": "382b7458-b96c-44d5-8827-b5b56cd20a21",
        "CreatedBy": "",
        "EventTitle": "Joseph Casa Super Bowl Party",
        "EventDate": "2019-02-03T00:00:00",
        "EventStartTime": "2019-01-26T15:30:00",
        "EventEndTime": "2019-01-26T21:00:00",
        "EventAddress1": "6591 North Lonicera Way, Meridian, ID, USA",
        "EventAddress2": "",
        "City": "Meridian",
        "State": "ID",
        "ZipCode": "",
        "LocationLatitude": 43.6646062,
        "LocationLongitude": -116.4428587,
        "EventMessage": "",
        "PrivacySettings": false,
        "CreateDate": "2019-01-26T20:18:40.623",
        "Venue": "Joseph House",
        "EventImage": "",
        "EventGUID": "154649b8-d313-4014-b9d6-5ab4ef42ac25",
        "ViewDate": null,
        "id": 49
    },
    {
        "EventId": 51,
        "UserTableGUID": "5232e9f3-2040-4c4d-bb87-739d8364cc64",
        "CreatedBy": "",
        "EventTitle": "Happy 5th Birthday Arabella!",
        "EventDate": "2019-02-10T00:00:00",
        "EventStartTime": "2019-01-31T12:00:00",
        "EventEndTime": "2019-01-31T14:00:00",
        "EventAddress1": "7204 Pearl Road, Middleburg Heights, OH, USA",
        "EventAddress2": "",
        "City": "Middleburg Heights",
        "State": "OH",
        "ZipCode": "",
        "LocationLatitude": 41.370204,
        "LocationLongitude": -81.8030585,
        "EventMessage": "",
        "PrivacySettings": false,
        "CreateDate": "2019-01-31T15:17:11.823",
        "Venue": "Get Air ",
        "EventImage": "",
        "EventGUID": "dcc95ec8-f8e2-4b13-b4ae-7372eeb770e1",
        "ViewDate": null,
        "id": 50
    },
    {
        "EventId": 52,
        "UserTableGUID": "656279e6-c8b3-4ed9-a4be-3550b6d52357",
        "CreatedBy": "",
        "EventTitle": "LET FREEDOM RING!",
        "EventDate": "2019-02-16T00:00:00",
        "EventStartTime": "2019-02-01T09:30:00",
        "EventEndTime": "2019-02-01T17:00:00",
        "EventAddress1": "449 Auburn Avenue Northeast, Atlanta, GA, USA",
        "EventAddress2": "",
        "City": "Atlanta",
        "State": "GA",
        "ZipCode": "",
        "LocationLatitude": 33.755313873291016,
        "LocationLongitude": -84.37297821044922,
        "EventMessage": "Join us on our black history excursion to The MLK Center and The Apex Museum . We will be traveling back in time to live a day in the life of Dr. Martin Luther King & learn more about our rich heritag",
        "PrivacySettings": true,
        "CreateDate": "2019-02-01T14:53:47.59",
        "Venue": "King Center And Apex Museum ",
        "EventImage": "",
        "EventGUID": "a6ab86c5-5864-440e-9126-d13858543f0a",
        "ViewDate": null,
        "id": 51
    },
    {
        "EventId": 53,
        "UserTableGUID": "656279e6-c8b3-4ed9-a4be-3550b6d52357",
        "CreatedBy": "",
        "EventTitle": "LET FREEDOM RING!",
        "EventDate": "2019-02-16T00:00:00",
        "EventStartTime": "2019-02-01T09:30:00",
        "EventEndTime": "2019-02-01T17:00:00",
        "EventAddress1": "449 Auburn Avenue Northeast, Atlanta, GA, USA",
        "EventAddress2": "",
        "City": "Atlanta",
        "State": "GA",
        "ZipCode": "",
        "LocationLatitude": 33.755313873291016,
        "LocationLongitude": -84.37297821044922,
        "EventMessage": "Come and join us on our “Black History” excursion to the MLK Center. Also, We will be exploring our rich Atlanta histiry by way of the historic Apex Museum.  Transportation will be provided at Southla",
        "PrivacySettings": true,
        "CreateDate": "2019-02-01T14:53:47.963",
        "Venue": "King Center And Apex Museum ",
        "EventImage": "",
        "EventGUID": "50ecf6e3-6848-47cc-b063-f7703018833b",
        "ViewDate": null,
        "id": 52
    },
    {
        "EventId": 54,
        "UserTableGUID": "656279e6-c8b3-4ed9-a4be-3550b6d52357",
        "CreatedBy": "",
        "EventTitle": "LET FREEDOM RING!",
        "EventDate": "2019-02-16T00:00:00",
        "EventStartTime": "2019-02-01T09:30:00",
        "EventEndTime": "2019-02-01T17:00:00",
        "EventAddress1": "449 Auburn Avenue Northeast, Atlanta, GA, USA",
        "EventAddress2": "",
        "City": "Atlanta",
        "State": "GA",
        "ZipCode": "",
        "LocationLatitude": 33.7553157,
        "LocationLongitude": -84.3729745,
        "EventMessage": "Join us on our black history excursion to The MLK Center and The Apex Museum . We will be traveling back in time to live a day in the life of Dr. Martin Luther King and learn more about our rich herit",
        "PrivacySettings": true,
        "CreateDate": "2019-02-01T14:54:28.103",
        "Venue": "King Center And Apex Museum ",
        "EventImage": "",
        "EventGUID": "c4e8c738-c7ab-4fa9-a9ed-4a22c0e25cbb",
        "ViewDate": null,
        "id": 53
    },
    {
        "EventId": 55,
        "UserTableGUID": "7958ce6f-4ba7-42ca-97da-4e6a098027e8",
        "CreatedBy": "",
        "EventTitle": "Kayden’s 12th Birthday",
        "EventDate": "2019-02-23T00:00:00",
        "EventStartTime": "2019-02-09T17:30:00",
        "EventEndTime": "2019-02-09T20:30:00",
        "EventAddress1": "1647 Mallory Ln, Brentwood, TN 37027, United States",
        "EventAddress2": "",
        "City": "Brentwood",
        "State": "TN",
        "ZipCode": "",
        "LocationLatitude": 35.972599029541016,
        "LocationLongitude": -86.81102752685547,
        "EventMessage": "“He came back like a survivor” Grab your Camo, bounce on over!",
        "PrivacySettings": false,
        "CreateDate": "2019-02-09T15:13:39.5",
        "Venue": "Above All ",
        "EventImage": "",
        "EventGUID": "e4ce15d8-09f5-4c21-b04b-95321d527bbd",
        "ViewDate": null,
        "id": 54
    },
    {
        "EventId": 56,
        "UserTableGUID": "8592669a-3ae7-4543-86b9-b42e3e18b418",
        "CreatedBy": "",
        "EventTitle": "Come brunch with Ivan ",
        "EventDate": "2019-02-17T00:00:00",
        "EventStartTime": "2019-02-09T12:00:00",
        "EventEndTime": "2019-02-09T15:00:00",
        "EventAddress1": "2021 North Hampton Road, DeSoto, TX, USA",
        "EventAddress2": "",
        "City": "DeSoto",
        "State": "TX",
        "ZipCode": "",
        "LocationLatitude": 32.630714,
        "LocationLongitude": -96.8582601,
        "EventMessage": "Come have brunch with me on my birthday. ",
        "PrivacySettings": false,
        "CreateDate": "2019-02-09T16:41:19.87",
        "Venue": "Brickhouse Lounge In Desoto",
        "EventImage": "",
        "EventGUID": "5a49c9e6-c90d-4427-a053-ce920ddee3e5",
        "ViewDate": null,
        "id": 55
    },
    {
        "EventId": 57,
        "UserTableGUID": "cdec6e92-7a4a-4f1a-9f78-a5d4b5e50518",
        "CreatedBy": "",
        "EventTitle": "Zara is turning 10!",
        "EventDate": "2019-02-12T00:00:00",
        "EventStartTime": "2019-02-12T08:10:00",
        "EventEndTime": "2019-02-12T08:09:00",
        "EventAddress1": "1/4-8 Lindsay st, Neutral Bay NSW",
        "EventAddress2": "",
        "City": "Neutral Bay",
        "State": "",
        "ZipCode": "",
        "LocationLatitude": 0,
        "LocationLongitude": 0,
        "EventMessage": "",
        "PrivacySettings": true,
        "CreateDate": "2019-02-11T20:54:26.243",
        "Venue": "Zara’s place",
        "EventImage": "",
        "EventGUID": "41a987b1-d155-487e-b498-5f48256c4a28",
        "ViewDate": null,
        "id": 56
    }
]